medetpy/__init__.py
medetpy/met.py
medetpy-1.2.4.dist-info/LICENSE.txt
medetpy-1.2.4.dist-info/METADATA
medetpy-1.2.4.dist-info/WHEEL
medetpy-1.2.4.dist-info/top_level.txt
medetpy-1.2.4.dist-info/RECORD
