Metadata-Version: 2.1
Name: medetpy
Version: 1.2.4
Summary: med-met
Home-page: https://github.com/MG/med-met
Author: Grant-M
Author-email: Grant_M@gmail.com
License: UNKNOWN
Platform: UNKNOWN
Classifier: Programming Language :: Python :: 3
Classifier: License :: OSI Approved :: MIT License
Classifier: Operating System :: OS Independent
Requires-Python: >=3.6
Requires-Dist: requests
Requires-Dist: medpy
